PyIR/__init__.py
PyIR/setup.py
PyIR/pyir/__init__.py
PyIR/pyir/arg_parse.py
PyIR/pyir/factory.py
PyIR/pyir/filters.py
PyIR/pyir/igblast.py
PyIR/pyir/output.py
PyIR/pyir/parsers.py
pygor3/AIRR.py
pygor3/IgorBestScenarios.py
pygor3/IgorDB.sql
pygor3/IgorDBBestScenariosVDJ.sql
pygor3/IgorDefaults.py
pygor3/IgorDictionaries.py
pygor3/IgorIO.py
pygor3/IgorIndexedSequence.py
pygor3/IgorIndexedSequencesDB.py
pygor3/IgorSQL.py
pygor3/IgorSqliteDB.py
pygor3/IgorSqliteDBBestScenarios.py
pygor3/__init__.py
pygor3/config.json
pygor3/config.py
pygor3/entropy.py
pygor3/imgt.py
pygor3/utils.py
pygor3/utils_pre_processing.py
pygor3/demo/data/IgL/IgL_seqs_memory_Functional.txt
pygor3/demo/data/IgL/IgL_seqs_memory_Nofunctional.txt
pygor3/demo/data/IgL/IgL_seqs_naive_Functional.txt
pygor3/demo/data/IgL/IgL_seqs_naive_Functional_small.txt
pygor3/demo/data/IgL/IgL_seqs_naive_Nofunctional.txt
pygor3/demo/notebooks/Documentation.ipynb
pygor3/demo/notebooks/Function_BestScenarios.ipynb
pygor3/demo/notebooks/HIP00110.tsv.gz
pygor3/demo/notebooks/IGoR_diagram.png
pygor3/demo/notebooks/Killifish_D_genes.fasta
pygor3/demo/notebooks/Killifish_Genomic_template_modifications.ipynb
pygor3/demo/notebooks/Killifish_J_anchors.csv
pygor3/demo/notebooks/Killifish_J_genes.fasta
pygor3/demo/notebooks/Killifish_V_anchors.csv
pygor3/demo/notebooks/Killifish_V_genes.fasta
pygor3/demo/notebooks/Killifish_example.ipynb
pygor3/demo/notebooks/QuickStart.ipynb
pygor3/demo/notebooks/Testing.ipynb
pygor3/demo/notebooks/Tutorial.ipynb
pygor3/demo/notebooks/d00_Configuration.ipynb
pygor3/demo/notebooks/d01_RunIGoR.ipynb
pygor3/demo/notebooks/d02_ExploringModels.ipynb
pygor3/demo/notebooks/d03_EditModel.ipynb
pygor3/demo/notebooks/d04_InferringNewModel.ipynb
pygor3/demo/notebooks/d11_Observables_2.ipynb
pygor3/demo/notebooks/d12_Observables_3.ipynb
pygor3/demo/notebooks/.ipynb_checkpoints/Function_BestScenarios-checkpoint.ipynb
pygor3/demo/notebooks/.ipynb_checkpoints/Testing-checkpoint.ipynb
pygor3-0.3.2.dist-info/LICENSE
pygor3-0.3.2.dist-info/METADATA
pygor3-0.3.2.dist-info/WHEEL
pygor3-0.3.2.dist-info/entry_points.txt
pygor3-0.3.2.dist-info/top_level.txt
pygor3-0.3.2.dist-info/RECORD
