Metadata-Version: 2.1
Name: pygor3
Version: 0.3.2
Summary: Python package to manipulate and run IGoR data files
Home-page: https://github.com/alfaceor/pygor3
Author: Carlos Olivares
Author-email: carlos.olivares@phys.ens.fr
License: GNU GPLv3
Platform: UNKNOWN
Requires-Python: >=3.5
License-File: LICENSE
Requires-Dist: pandas
Requires-Dist: numpy
Requires-Dist: xarray
Requires-Dist: beautifulsoup4
Requires-Dist: biopython
Requires-Dist: Click
Requires-Dist: networkx
Requires-Dist: requests
Requires-Dist: matplotlib
Requires-Dist: airr
Requires-Dist: appdirs
Requires-Dist: importlib-resources ; python_version < "3.7"
